greenland/__init__.py
greenland/conventions.py
greenland/cmdline/__init__.py
greenland/cmdline/commandpackages.py
greenland/cmdline/mixins.py
greenland/cmdline/parsers.py
greenland/cmdline/scriptomatic.py
greenland/cmdline/shellcommands.py
greenland/cmdline/specification2.py
greenland/cmdline/tools.py
greenland/cmdline/sketches/__init__.py
greenland/filesystem/__init__.py
greenland/filesystem/find.py
greenland/filesystem/trees.py
greenland/filesystem/sketches/__init__.py
greenland/filesystem/sketches/sk_model.py
greenland/metaprogramming/__init__.py
greenland/metaprogramming/definition_order.py
greenland/parsing/__init__.py
greenland/parsing/master_regex.py
greenland/parsing/sketches/__init__.py
greenland/toolbox/__init__.py
greenland/toolbox/predicates.py
greenland/toolbox/structs.py
greenland-0.0.5.dist-info/LICENSE.txt
greenland-0.0.5.dist-info/METADATA
greenland-0.0.5.dist-info/WHEEL
greenland-0.0.5.dist-info/top_level.txt
greenland-0.0.5.dist-info/RECORD
