Metadata-Version: 2.1
Name: greenland
Version: 0.0.5
Summary: A pythonic scripting environment
Home-page: https://github.com/m-e-leypold/greenland4
Author: Markus E Leypold
Author-email: greenland-4sda212@m-e-leypold.de
License: UNKNOWN
Platform: UNKNOWN
Classifier: Programming Language :: Python :: 3
Classifier: License :: OSI Approved :: GNU General Public License v3 or later (GPLv3+)
Classifier: Operating System :: OS Independent
